[
  {
    "type": "pose",
    "pos": [
      6250,
      -5950,
      -4050,
      6250,
      0,
      -3000
    ]
  },
  {
    "type": "pose",
    "pos": [
      4050,
      231,
      -2970,
      4050,
      -280,
      -2940
    ]
  },
  {
    "type": "delay",
    "ms": 500
  },
  {
    "type": "pose",
    "pos": [
      3640,
      231,
      -3160,
      3640,
      -300,
      -2940
    ]
  },
  {
    "type": "delay",
    "ms": 500
  },
  {
    "type": "pose",
    "pos": [
      3640,
      231,
      -3160,
      3640,
      30,
      -2940
    ]
  },
  {
    "type": "delay",
    "ms": 500
  },
  {
    "type": "pose",
    "pos": [
      4290,
      191,
      -2900,
      4290,
      30,
      -2940
    ]
  },
  {
    "type": "pose",
    "pos": [
      4890,
      191,
      -2550,
      4890,
      30,
      -2940
    ]
  },
  {
    "type": "pose",
    "pos": [
      5440,
      191,
      -2400,
      5440,
      30,
      -2940
    ]
  },
  {
    "type": "pose",
    "pos": [
      5540,
      191,
      -2350,
      5540,
      30,
      -2940
    ]
  },
  {
    "type": "pose",
    "pos": [
      6640,
      191,
      -2250,
      6640,
      30,
      -2940
    ]
  }
]